foolscap/__init__.py
foolscap/_version.py
foolscap/api.py
foolscap/banana.py
foolscap/base32.py
foolscap/broker.py
foolscap/call.py
foolscap/connection.py
foolscap/constraint.py
foolscap/copyable.py
foolscap/crypto.py
foolscap/eventual.py
foolscap/furl.py
foolscap/info.py
foolscap/ipb.py
foolscap/negotiate.py
foolscap/observer.py
foolscap/pb.py
foolscap/promise.py
foolscap/py.typed
foolscap/reconnector.py
foolscap/referenceable.py
foolscap/remoteinterface.py
foolscap/schema.py
foolscap/slicer.py
foolscap/storage.py
foolscap/stringchain.py
foolscap/tokens.py
foolscap/util.py
foolscap/vocab.py
foolscap/appserver/__init__.py
foolscap/appserver/cli.py
foolscap/appserver/client.py
foolscap/appserver/server.py
foolscap/appserver/services.py
foolscap/connections/__init__.py
foolscap/connections/i2p.py
foolscap/connections/tcp.py
foolscap/connections/tor.py
foolscap/logging/__init__.py
foolscap/logging/app_versions.py
foolscap/logging/cli.py
foolscap/logging/dumper.py
foolscap/logging/filter.py
foolscap/logging/flogfile.py
foolscap/logging/gatherer.py
foolscap/logging/incident.py
foolscap/logging/interfaces.py
foolscap/logging/levels.py
foolscap/logging/log.py
foolscap/logging/publish.py
foolscap/logging/tail.py
foolscap/logging/web.py
foolscap/slicers/__init__.py
foolscap/slicers/allslicers.py
foolscap/slicers/bool.py
foolscap/slicers/decimal_slicer.py
foolscap/slicers/dict.py
foolscap/slicers/list.py
foolscap/slicers/none.py
foolscap/slicers/root.py
foolscap/slicers/set.py
foolscap/slicers/tuple.py
foolscap/slicers/unicode.py
foolscap/slicers/vocab.py
foolscap/test/__init__.py
foolscap/test/apphelper.py
foolscap/test/bench_banana.py
foolscap/test/check-connections-client.py
foolscap/test/check-connections-server.py
foolscap/test/common.py
foolscap/test/run_trial.py
foolscap/test/test__versions.py
foolscap/test/test_appserver.py
foolscap/test/test_banana.py
foolscap/test/test_call.py
foolscap/test/test_connection.py
foolscap/test/test_copyable.py
foolscap-24.9.0.dist-info/LICENSE
foolscap-24.9.0.dist-info/METADATA
foolscap-24.9.0.dist-info/WHEEL
foolscap-24.9.0.dist-info/entry_points.txt
foolscap-24.9.0.dist-info/top_level.txt
foolscap-24.9.0.dist-info/RECORD
